{
  "date": "2026-05-23",
  "finalized": false,
  "peak_mw_affected": 170,
  "peak_time": "02:04",
  "interruption_minutes": null,
  "emergency_mw": null,
  "block_outage_minutes": {
    "1": 155,
    "2": 0,
    "3": 0,
    "4": 1365,
    "5": 0,
    "6": 0
  },
  "total_block_outage_minutes": 1520,
  "daf_count": 0,
  "sen_collapse_count": 0,
  "sen_outage_minutes": 0,
  "sen_outage": false,
  "partial_sen_collapse_count": 0,
  "partial_sen_reconnect_count": 0,
  "partial_sen_outage_minutes": 0,
  "cte_offline_minutes": {},
  "averias_count_by_municipio": {
    "Arroyo Naranjo": 1,
    "Habana Del Este": 1,
    "Lisa": 1
  },
  "averias_total": 3,
  "source_msg_count": 12,
  "by_type_counts": {
    "actualizacion_bloques": 3,
    "inicio_afectacion": 1,
    "averias": 3,
    "restablecimiento_gradual": 3,
    "disparo_circuito": 1,
    "empty": 1
  }
}
