{
  "date": "2026-05-19",
  "finalized": false,
  "peak_mw_affected": 491,
  "peak_time": "21:10",
  "interruption_minutes": 1440,
  "emergency_mw": 125,
  "block_outage_minutes": {
    "1": 240,
    "2": 263,
    "3": 4,
    "4": 0,
    "5": 0,
    "6": 0
  },
  "total_block_outage_minutes": 507,
  "daf_count": 3,
  "sen_collapse_count": 0,
  "sen_outage_minutes": 0,
  "sen_outage": false,
  "cte_offline_minutes": {},
  "averias_count_by_municipio": {
    "Marianao": 3,
    "Lisa": 2,
    "Arroyo Naranjo": 1,
    "Regla": 1,
    "Guanabacoa": 1,
    "Habana Del Este": 1
  },
  "averias_total": 9,
  "source_msg_count": 54,
  "by_type_counts": {
    "averias": 7,
    "actualizacion_bloques": 9,
    "restablecimiento": 10,
    "disparo_circuito": 7,
    "inicio_afectacion": 2,
    "daf": 3,
    "restablecimiento_daf": 2,
    "sen_update": 1,
    "otro": 4,
    "transferencia_bloque": 3,
    "nota_diaria": 1,
    "via_libre": 3,
    "empty": 1,
    "corto": 1
  }
}
