{
  "month": "2023-02",
  "finalized": true,
  "dailies_count": 28,
  "avg_peak_mw": 1413.0,
  "max_peak_mw": 1413,
  "total_interruption_minutes": 0,
  "total_block_outage_minutes": {
    "1": 0,
    "2": 0,
    "3": 0,
    "4": 0,
    "5": 0,
    "6": 0
  },
  "total_emergency_mw_sum": 0,
  "averias_count_by_municipio": {
    "Cerro De Las Áreas De Calzada De Buenos Aires Y La Zona De Agua Dulce Están Presentando Disparo Del Circuito": 1,
    "Cerro": 1,
    "Boyeros": 1
  },
  "averias_total": 3,
  "daf_total": 25,
  "sen_outage_days": 13,
  "sen_outage_minutes_total": 9939,
  "cte_offline_minutes_total": {}
}
