{
  "month": "2026-06",
  "finalized": false,
  "dailies_count": 24,
  "avg_peak_mw": 366.1,
  "max_peak_mw": 526,
  "total_interruption_minutes": 0,
  "total_block_outage_minutes": {
    "1": 11378,
    "2": 6684,
    "3": 6408,
    "4": 9621,
    "5": 10780,
    "6": 9119
  },
  "total_emergency_mw_sum": 0,
  "averias_count_by_municipio": {
    "Guanabacoa": 8,
    "Lisa": 7,
    "Boyeros": 6,
    "Marianao": 6,
    "Habana Del Este": 5,
    "Cerro": 4,
    "Plaza": 4,
    "Arroyo Naranjo": 3,
    "Centro Habana": 3,
    "Cotorro": 3,
    "San Miguel Del Padrón": 1,
    "La Lisa": 1
  },
  "averias_total": 51,
  "daf_total": 17,
  "sen_collapse_total": 0,
  "sen_outage_days": 0,
  "sen_outage_minutes_total": 0,
  "partial_sen_collapse_total": 0,
  "partial_sen_outage_minutes_total": 0,
  "cte_offline_minutes_total": {}
}
