{
  "month": "2026-06",
  "finalized": false,
  "dailies_count": 24,
  "avg_peak_mw": 362.8,
  "max_peak_mw": 526,
  "total_interruption_minutes": 0,
  "total_block_outage_minutes": {
    "1": 12268,
    "2": 7439,
    "3": 7313,
    "4": 10731,
    "5": 11098,
    "6": 10069
  },
  "total_emergency_mw_sum": 0,
  "averias_count_by_municipio": {
    "Guanabacoa": 8,
    "Boyeros": 7,
    "Lisa": 7,
    "Marianao": 6,
    "Habana Del Este": 5,
    "Cerro": 4,
    "Plaza": 4,
    "Cotorro": 3,
    "Arroyo Naranjo": 2,
    "Centro Habana": 2,
    "San Miguel Del Padrón": 1
  },
  "averias_total": 49,
  "daf_total": 17,
  "sen_collapse_total": 0,
  "sen_outage_days": 0,
  "sen_outage_minutes_total": 0,
  "partial_sen_collapse_total": 0,
  "partial_sen_outage_minutes_total": 0,
  "cte_offline_minutes_total": {}
}
